CHANGES.rst
MANIFEST.in
README.rst
setup.py
asa/__init__.py
asa/asa.py
asa.egg-info/PKG-INFO
asa.egg-info/SOURCES.txt
asa.egg-info/dependency_links.txt
asa.egg-info/top_level.txt