Metadata-Version: 1.1
Name: asa
Version: 0.1.2
Summary: Japanese Argument Structure Analyzer (ASA) client for Python
Home-page: https://github.com/ikegami-yukino/asa-python
Author: Yukino Ikegami
Author-email: yknikgm@gmail.com
License: MIT License
Keywords: argument structure analyzer
Platform: POSIX
Platform: Windows
Platform: Unix
Platform: MacOS
Classifier: Development Status :: 3 - Alpha
Classifier: Intended Audience :: Developers
Classifier: Intended Audience :: Information Technology
Classifier: License :: OSI Approved :: MIT License
Classifier: Natural Language :: Japanese
Classifier: Programming Language :: Python :: 2.6
Classifier: Programming Language :: Python :: 2.7
Classifier: Programming Language :: Python :: 3.3
Classifier: Programming Language :: Python :: 3.4
Classifier: Programming Language :: Python :: 3.5
Classifier: Programming Language :: Python :: 3.6
Classifier: Topic :: Text Processing :: Linguistic
